argus/__init__.py
argus/formatters.py
argus/handlers.py
argus/log_functions.py
argus_logging-2.3.3.dist-info/METADATA
argus_logging-2.3.3.dist-info/WHEEL
argus_logging-2.3.3.dist-info/RECORD
