Metadata-Version: 2.3
Name: argus-logging
Version: 2.3.3
Summary: A module to simplify logging
License: MIT
Keywords: python,logging
Author: Michael Knowles
Requires-Python: >=3.9
Classifier: License :: OSI Approved :: MIT License
Classifier: Programming Language :: Python :: 3
Classifier: Programming Language :: Python :: 3.9
Classifier: Programming Language :: Python :: 3.10
Classifier: Programming Language :: Python :: 3.11
Classifier: Programming Language :: Python :: 3.12
Classifier: Programming Language :: Python :: 3.13
Project-URL: Documentation, https://mapledyne.github.io/argus-logging/
Project-URL: Source, https://github.com/mapledyne/argus-logging/
